museumpy/__init__.py
museumpy/client.py
museumpy/errors.py
museumpy/response.py
museumpy/xmlparse.py
museumpy-0.4.1.dist-info/LICENSE.md
museumpy-0.4.1.dist-info/METADATA
museumpy-0.4.1.dist-info/WHEEL
museumpy-0.4.1.dist-info/top_level.txt
museumpy-0.4.1.dist-info/RECORD
