Metadata-Version: 2.1
Name: museumpy
Version: 0.4.1
Summary: Client for MuseumPlus
Home-page: https://github.com/metaodi/museumpy
Author: Stefan Oderbolz
Author-email: odi@metaodi.ch
Maintainer: Stefan Oderbolz
Maintainer-email: odi@metaodi.ch
License: MIT
Download-URL: https://github.com/metaodi/museumpy/archive/v0.4.1.zip
Keywords: museumplus,glam,museum,zetcom
Platform: UNKNOWN
Classifier: License :: OSI Approved :: MIT License
Classifier: Intended Audience :: Developers
Classifier: Topic :: Software Development :: Libraries
Classifier: Development Status :: 4 - Beta
Classifier: Programming Language :: Python :: 3.6
Classifier: Programming Language :: Python :: 3.7
Classifier: Programming Language :: Python :: 3.8
Requires-Python: >=3.6
Requires-Dist: requests
Requires-Dist: defusedxml
Requires-Dist: xmltodict
